[
  {
    "id": 1,
    "slug": "CryptoCats",
    "name": "Crypto Cats",
    "symbol": "CATS",
    "category": "Game",
    "description": "Discover the CryptoCats",
    "NftsAddress": "0xD5601825b62D347D07E796b6E8Ed9fAf30AA86A8",
    "StakingAddress": "0xF10BbD2a1F36d354e170390ACE934Cc16217E9ef",
    "RewardsAddress": "0xA53f0505e699c96DBF44CDBc00c022d5Bc6D8b7C",
    "NftsContract": "MyAwesomeNFT_witheList",
    "StakingContract": "Staking",
    "RewardsContract": "RewardToken",
    "openSeaBaseUrl": "https://testnets.opensea.io/fr/assets/mumbai/",
    "collectionBaseUrl": "https://testnets.opensea.io/fr/collection/cryptocats-vj7a53l4oh",
    "farmable": true,
    "collectionLogo": "/img/hidden.jpeg",
    "blockchainLogo": "/img/polygon-matic-logo.png"
  }
]
